image_jointer/__init__.py
image_jointer/image_jointer.py
image_jointer/utils.py
image_jointer/base/adapter.py
image_jointer/base/blank.py
image_jointer/base/enums.py
image_jointer/base/figure.py
image_jointer/base/part.py
image_jointer/base/vector.py
image_jointer-2.1.dist-info/LICENSE
image_jointer-2.1.dist-info/METADATA
image_jointer-2.1.dist-info/WHEEL
image_jointer-2.1.dist-info/top_level.txt
image_jointer-2.1.dist-info/RECORD
