Metadata-Version: 2.1
Name: image_jointer
Version: 2.1
Summary: Build up image by jointing images
Author: Nanahuse
License: MIT License
Project-URL: Homepage, https://github.com/Nanahuse/ImageJointer
Classifier: License :: OSI Approved :: MIT License
Requires-Python: >=3.10
License-File: LICENSE
Requires-Dist: pillow >=10.0.0
Provides-Extra: dev
Requires-Dist: pytest ; extra == 'dev'
Requires-Dist: flake8 ; extra == 'dev'
Requires-Dist: black ; extra == 'dev'
Requires-Dist: isort ; extra == 'dev'
Requires-Dist: mypy ; extra == 'dev'
Requires-Dist: types-pillow ; extra == 'dev'
